avnet/iotconnect/restapi/__init__.py
avnet/iotconnect/restapi/cli/__init__.py
avnet/iotconnect/restapi/cli/main.py
avnet/iotconnect/restapi/lib/__init__.py
avnet/iotconnect/restapi/lib/accesstoken.py
avnet/iotconnect/restapi/lib/apirequest.py
avnet/iotconnect/restapi/lib/apiurl.py
avnet/iotconnect/restapi/lib/command.py
avnet/iotconnect/restapi/lib/config.py
avnet/iotconnect/restapi/lib/credentials.py
avnet/iotconnect/restapi/lib/device.py
avnet/iotconnect/restapi/lib/entity.py
avnet/iotconnect/restapi/lib/error.py
avnet/iotconnect/restapi/lib/firmware.py
avnet/iotconnect/restapi/lib/ota.py
avnet/iotconnect/restapi/lib/storage.py
avnet/iotconnect/restapi/lib/template.py
avnet/iotconnect/restapi/lib/upgrade.py
avnet/iotconnect/restapi/lib/user.py
avnet/iotconnect/restapi/lib/util.py
iotconnect_rest_api-2.1.0.dist-info/METADATA
iotconnect_rest_api-2.1.0.dist-info/WHEEL
iotconnect_rest_api-2.1.0.dist-info/entry_points.txt
iotconnect_rest_api-2.1.0.dist-info/top_level.txt
iotconnect_rest_api-2.1.0.dist-info/RECORD
