Metadata-Version: 2.4
Name: iotconnect-rest-api
Version: 2.1.0
Summary: Avnet IoTConnect Rest API
Author-email: Nik Markovic <nikola.markovic@avnet.com>
Project-URL: Homepage, https://github.com/avnet-iotconnect/iotc-python-rest-api
Keywords: IoTconnect,AWS,IoTCore,Azure,IoTHub
Classifier: Development Status :: 3 - Alpha
Classifier: Intended Audience :: Developers
Classifier: License :: OSI Approved :: MIT License
Classifier: Natural Language :: English
Classifier: Operating System :: MacOS :: MacOS X
Classifier: Operating System :: Microsoft :: Windows
Classifier: Operating System :: POSIX
Classifier: Programming Language :: Python
Classifier: Programming Language :: Python :: 3.11
Classifier: Programming Language :: Python :: 3.12
Classifier: Topic :: Communications
Classifier: Topic :: Internet
Requires-Python: >=3.11
Requires-Dist: requests>=2.32.3
Requires-Dist: platformdirs>=4.3.6
Requires-Dist: jmespath>=1.0.1
Requires-Dist: cryptography>=44.0.0
